pycbc/transforms.py
pycbc/mchirp_area.py
pycbc/version.py
pycbc/bin_utils.py
pycbc/_version.py
pycbc/boundaries.py
pycbc/conversions.py
pycbc/rate.py
pycbc/__init__.py
pycbc/dq.py
pycbc/opt.py
pycbc/sensitivity.py
pycbc/pnutils.py
pycbc/_version_helper.py
pycbc/pool.py
pycbc/cosmology.py
pycbc/libutils.py
pycbc/scheme.py
pycbc/types/array_cpu.cpython-311-darwin.so
pycbc/types/array_cuda.py
pycbc/types/config.py
pycbc/types/frequencyseries.py
pycbc/types/array_cupy.py
pycbc/types/aligned.py
pycbc/types/__init__.py
pycbc/types/optparse.py
pycbc/types/array.py
pycbc/types/timeseries.py
pycbc/strain/__init__.py
pycbc/strain/lines.py
pycbc/strain/gate.py
pycbc/strain/recalibrate.py
pycbc/strain/strain.py
pycbc/strain/calibration.py
pycbc/coordinates/__init__.py
pycbc/coordinates/space.py
pycbc/coordinates/base.py
pycbc/inject/injfilterrejector.py
pycbc/inject/__init__.py
pycbc/inject/inject.py
pycbc/psd/analytical.py
pycbc/psd/__init__.py
pycbc/psd/estimate.py
pycbc/psd/analytical_space.py
pycbc/psd/variation.py
pycbc/psd/read.py
pycbc/neutron_stars/pg_isso_solver.py
pycbc/neutron_stars/__init__.py
pycbc/neutron_stars/eos_utils.py
pycbc/neutron_stars/ns_data/equil_2H.dat
pycbc/tmpltbank/bank_output_utils.py
pycbc/tmpltbank/lattice_utils.py
pycbc/tmpltbank/coord_utils.py
pycbc/tmpltbank/__init__.py
pycbc/tmpltbank/bank_conversions.py
pycbc/tmpltbank/lambda_mapping.py
pycbc/tmpltbank/partitioned_bank.py
pycbc/tmpltbank/option_utils.py
pycbc/tmpltbank/sky_grid.py
pycbc/tmpltbank/brute_force_methods.py
pycbc/tmpltbank/calc_moments.py
pycbc/catalog/catalog.py
pycbc/catalog/__init__.py
pycbc/io/ligolw.py
pycbc/io/hdf.py
pycbc/io/__init__.py
pycbc/io/record.py
pycbc/io/live.py
pycbc/io/gracedb.py
pycbc/frame/store.py
pycbc/frame/__init__.py
pycbc/frame/gwosc.py
pycbc/frame/frame.py
pycbc/population/rates_functions.py
pycbc/population/__init__.py
pycbc/population/fgmc_plots.py
pycbc-2.9.0.dist-info/RECORD
pycbc-2.9.0.dist-info/WHEEL
pycbc-2.9.0.dist-info/top_level.txt
pycbc-2.9.0.dist-info/METADATA
pycbc-2.9.0.dist-info/licenses/LICENSE
