Metadata-Version: 2.4
Name: PyCBC
Version: 2.9.0
Summary: Core library to analyze gravitational-wave data, find signals, and study their parameters.
Home-page: http://pycbc.org/
Download-URL: https://github.com/gwastro/pycbc/tarball/v2.9.0
Author: The PyCBC team
Author-email: alex.nitz@gmail.org
Keywords: ligo,physics,gravity,signal processing,gravitational waves
Classifier: Programming Language :: Python
Classifier: Programming Language :: Python :: 3.9
Classifier: Programming Language :: Python :: 3.10
Classifier: Programming Language :: Python :: 3.11
Classifier: Programming Language :: Python :: 3.12
Classifier: Intended Audience :: Science/Research
Classifier: Natural Language :: English
Classifier: Topic :: Scientific/Engineering
Classifier: Topic :: Scientific/Engineering :: Astronomy
Classifier: Topic :: Scientific/Engineering :: Physics
Classifier: License :: OSI Approved :: GNU General Public License v3 (GPLv3)
Requires-Python: >=3.9
License-File: LICENSE
Requires-Dist: numpy>=1.16.0
Requires-Dist: cython>=0.29
Requires-Dist: numpy!=1.19.0,!=2.2.2,>=1.16.0
Requires-Dist: scipy>=0.16.0
Requires-Dist: astropy!=4.0.5,!=4.2.1,>=2.0.3
Requires-Dist: matplotlib>=1.5.1
Requires-Dist: mpld3>=0.3
Requires-Dist: pillow
Requires-Dist: h5py!=3.7.0,>=3.0.0
Requires-Dist: jinja2
Requires-Dist: Mako>=1.0.1
Requires-Dist: beautifulsoup4>=4.6.0
Requires-Dist: tqdm
Requires-Dist: setuptools
Requires-Dist: gwdatafind
Requires-Dist: pegasus-wms.api>=5.1.1
Requires-Dist: igwn-ligolw<2.1.0
Requires-Dist: igwn-segments
Requires-Dist: lalsuite!=7.2
Requires-Dist: lscsoft-glue>=1.59.3
Requires-Dist: pykerr
Provides-Extra: cuda
Requires-Dist: pycuda>=2015.1; extra == "cuda"
Requires-Dist: scikit-cuda; extra == "cuda"
Provides-Extra: igwn
Requires-Dist: ciecplib>=0.7.0; extra == "igwn"
Dynamic: author
Dynamic: author-email
Dynamic: classifier
Dynamic: description
Dynamic: description-content-type
Dynamic: download-url
Dynamic: home-page
Dynamic: keywords
Dynamic: license-file
Dynamic: provides-extra
Dynamic: requires-dist
Dynamic: requires-python
Dynamic: summary
